{
  "appData": {
    "name": "罗德岛日常"
  },
  "timestamp": 1559550287110,
  "data": {
    "diversionConfig": [],
    "operationInfo": [
      {
        "minVersion": "4.3.0",
        "maxVersion": "9.9.0",
        "platform": 0,
        "valid": 1,
        "isShow": 1,
        "price": 0,
        "isFree": 0,
        "limitFreeBeginTime": "",
        "limitFreeEndTime": "",
        "validity": 0,
        "productId": "",
        "whiteList": "",
        "_id": "5cf4d93d53b4b631809ac4fb",
        "id": "5cf4d93d53b4b631809ac4fb"
      }
    ],
    "diyEmojiCommonText": [],
    "baseInfo": [
      {
        "name": "罗德岛日常",
        "type": 3,
        "ringType": 0,
        "feeType": 1,
        "tag": "可爱 呆萌 游戏",
        "label": [
          ""
        ],
        "desc": "干员在罗德岛的普通日常。",
        "icon": 0,
        "validArea": 3,
        "authorId": 0,
        "providerId": 0,
        "sougou": 1,
        "qzone": 1,
        "updateTipWording": "",
        "updateTipBeginTime": 0,
        "updateTipEndTime": 0,
        "realSize": 484978,
        "valid": 1,
        "sex": 1,
        "favourite": 1,
        "validBefore": "",
        "childMagicEmojiId": "",
        "isOriginal": 1,
        "isApng": 0,
        "QQgif": 0,
        "zip": "bq.zip",
        "_id": "5cf4d93d53b4b631809ac4fa",
        "id": "5cf4d93d53b4b631809ac4fa"
      }
    ],
    "additionInfo": [
      {
        "emojiId": "嗯",
        "keyword": "嗯",
        "order": 1,
        "wordingText": [
          "[]"
        ],
        "_id": "5cf4d93d53b4b631809ac4ea",
        "id": "5cf4d93d53b4b631809ac4ea"
      },
      {
        "emojiId": "在吗",
        "keyword": "在吗",
        "order": 2,
        "wordingText": [
          "[]"
        ],
        "_id": "5cf4d93d53b4b631809ac4eb",
        "id": "5cf4d93d53b4b631809ac4eb"
      },
      {
        "emojiId": "摸摸",
        "keyword": "摸摸",
        "order": 3,
        "wordingText": [
          "[]"
        ],
        "_id": "5cf4d93d53b4b631809ac4ec",
        "id": "5cf4d93d53b4b631809ac4ec"
      },
      {
        "emojiId": "醒了",
        "keyword": "醒了",
        "order": 4,
        "wordingText": [
          "[]"
        ],
        "_id": "5cf4d93d53b4b631809ac4ed",
        "id": "5cf4d93d53b4b631809ac4ed"
      },
      {
        "emojiId": "不是",
        "keyword": "不是",
        "order": 5,
        "wordingText": [
          "[]"
        ],
        "_id": "5cf4d93d53b4b631809ac4ee",
        "id": "5cf4d93d53b4b631809ac4ee"
      },
      {
        "emojiId": "emmm",
        "keyword": "emmm",
        "order": 6,
        "wordingText": [
          "[]"
        ],
        "_id": "5cf4d93d53b4b631809ac4ef",
        "id": "5cf4d93d53b4b631809ac4ef"
      },
      {
        "emojiId": "重做",
        "keyword": "重做",
        "order": 7,
        "wordingText": [
          "[]"
        ],
        "_id": "5cf4d93d53b4b631809ac4f0",
        "id": "5cf4d93d53b4b631809ac4f0"
      },
      {
        "emojiId": "睡了",
        "keyword": "睡了",
        "order": 8,
        "wordingText": [
          "[]"
        ],
        "_id": "5cf4d93d53b4b631809ac4f1",
        "id": "5cf4d93d53b4b631809ac4f1"
      },
      {
        "emojiId": "哈哈哈",
        "keyword": "哈哈哈",
        "order": 9,
        "wordingText": [
          "[]"
        ],
        "_id": "5cf4d93d53b4b631809ac4f2",
        "id": "5cf4d93d53b4b631809ac4f2"
      },
      {
        "emojiId": "累了",
        "keyword": "累了",
        "order": 10,
        "wordingText": [
          "[]"
        ],
        "_id": "5cf4d93d53b4b631809ac4f3",
        "id": "5cf4d93d53b4b631809ac4f3"
      },
      {
        "emojiId": "吃",
        "keyword": "吃",
        "order": 11,
        "wordingText": [
          "[]"
        ],
        "_id": "5cf4d93d53b4b631809ac4f4",
        "id": "5cf4d93d53b4b631809ac4f4"
      },
      {
        "emojiId": "疑问",
        "keyword": "疑问",
        "order": 12,
        "wordingText": [
          "[]"
        ],
        "_id": "5cf4d93d53b4b631809ac4f5",
        "id": "5cf4d93d53b4b631809ac4f5"
      },
      {
        "emojiId": "喝水",
        "keyword": "喝水",
        "order": 13,
        "wordingText": [
          "[]"
        ],
        "_id": "5cf4d93d53b4b631809ac4f6",
        "id": "5cf4d93d53b4b631809ac4f6"
      },
      {
        "emojiId": "上吧",
        "keyword": "上吧",
        "order": 14,
        "wordingText": [
          "[]"
        ],
        "_id": "5cf4d93d53b4b631809ac4f7",
        "id": "5cf4d93d53b4b631809ac4f7"
      },
      {
        "emojiId": "察觉",
        "keyword": "察觉",
        "order": 15,
        "wordingText": [
          "[]"
        ],
        "_id": "5cf4d93d53b4b631809ac4f8",
        "id": "5cf4d93d53b4b631809ac4f8"
      },
      {
        "emojiId": "回家",
        "keyword": "回家",
        "order": 16,
        "wordingText": [
          "[]"
        ],
        "_id": "5cf4d93d53b4b631809ac4f9",
        "id": "5cf4d93d53b4b631809ac4f9"
      }
    ],
    "md5Info": [
      {
        "name": "在吗",
        "md5": "9576e952cc16623d986c78dbdc471ba6"
      },
      {
        "name": "摸摸",
        "md5": "b2627cdbe329424ab8fe203e18ad9d62"
      },
      {
        "name": "醒了",
        "md5": "14c7a371a4c0183d37f61886f6cb2776"
      },
      {
        "name": "不是",
        "md5": "6b19c767e73ab190f824ba3db3b63e6c"
      },
      {
        "name": "emmm",
        "md5": "5a23d281a71c6a45fdd63b51a1c0f22a"
      },
      {
        "name": "重做",
        "md5": "dfe9d17dd420351d4eedc950007a80a9"
      },
      {
        "name": "睡了",
        "md5": "bbc61b6df21b5d56de0204cd68dcd54f"
      },
      {
        "name": "哈哈哈",
        "md5": "9b9b8bef3f22042a046c12b12ea04037"
      },
      {
        "name": "累了",
        "md5": "cbf6105ac7305e63aa5d217c460d8b2c"
      },
      {
        "name": "吃",
        "md5": "772f7fc6496fdc507442e2d252129dab"
      },
      {
        "name": "疑问",
        "md5": "8616f271a3963bda6c8c23c17efc4c8d"
      },
      {
        "name": "喝水",
        "md5": "dce6935950dd4f23e98c1e8ddc0c1bfc"
      },
      {
        "name": "上吧",
        "md5": "405b77634934c9cbc2cb51ac85278a9b"
      },
      {
        "name": "察觉",
        "md5": "f607de0f95301b05715c9c29eec27811"
      },
      {
        "name": "回家",
        "md5": "f599e332543ea4d534b1f1b9b3747606"
      },
      {
        "name": "嗯",
        "md5": "8606abddcc4da660cfa769cb79c3e8a8"
      }
    ],
    "__bgColors": {}
  }
}
