{
  "appData": {
    "name": "明日方舟 趣闻二"
  },
  "timestamp": 1577416202396,
  "data": {
    "diversionConfig": [],
    "operationInfo": [
      {
        "minVersion": "4.3.0",
        "maxVersion": "9.9.0",
        "platform": 0,
        "valid": 1,
        "isShow": 1,
        "price": 0,
        "isFree": 0,
        "limitFreeBeginTime": "",
        "limitFreeEndTime": "",
        "validity": 0,
        "productId": "",
        "whiteList": "",
        "_id": "5e05760059cad03694db1346",
        "id": "5e05760059cad03694db1346"
      }
    ],
    "diyEmojiCommonText": [],
    "baseInfo": [
      {
        "name": "明日方舟 趣闻二",
        "type": 3,
        "ringType": 0,
        "feeType": 1,
        "tag": "搞笑 可爱 萌",
        "label": [
          ""
        ],
        "desc": "干员的日常",
        "icon": 0,
        "validArea": 3,
        "authorId": 0,
        "providerId": 0,
        "sougou": 1,
        "qzone": 1,
        "updateTipWording": "",
        "updateTipBeginTime": 0,
        "updateTipEndTime": 0,
        "realSize": 491582,
        "valid": 1,
        "sex": 1,
        "favourite": 1,
        "validBefore": "",
        "childMagicEmojiId": "",
        "isOriginal": 1,
        "isApng": 0,
        "QQgif": 0,
        "zip": "bq.zip",
        "_id": "5e05760059cad03694db1345",
        "id": "5e05760059cad03694db1345"
      }
    ],
    "additionInfo": [
      {
        "emojiId": "问号",
        "keyword": "问号",
        "order": 1,
        "wordingText": [
          "[]"
        ],
        "fontcolor": "",
        "backcolor": "",
        "heightItems": "",
        "emojilabel": "",
        "_id": "5e05760059cad03694db1335",
        "id": "5e05760059cad03694db1335"
      },
      {
        "emojiId": "认真",
        "keyword": "认真",
        "order": 2,
        "wordingText": [
          "[]"
        ],
        "fontcolor": "",
        "backcolor": "",
        "heightItems": "",
        "emojilabel": "",
        "_id": "5e05760059cad03694db1336",
        "id": "5e05760059cad03694db1336"
      },
      {
        "emojiId": "你说什么",
        "keyword": "你说什么",
        "order": 3,
        "wordingText": [
          "[]"
        ],
        "fontcolor": "",
        "backcolor": "",
        "heightItems": "",
        "emojilabel": "",
        "_id": "5e05760059cad03694db1337",
        "id": "5e05760059cad03694db1337"
      },
      {
        "emojiId": "咻",
        "keyword": "咻",
        "order": 4,
        "wordingText": [
          "[]"
        ],
        "fontcolor": "",
        "backcolor": "",
        "heightItems": "",
        "emojilabel": "",
        "_id": "5e05760059cad03694db1338",
        "id": "5e05760059cad03694db1338"
      },
      {
        "emojiId": "哥俩好",
        "keyword": "哥俩好",
        "order": 5,
        "wordingText": [
          "[]"
        ],
        "fontcolor": "",
        "backcolor": "",
        "heightItems": "",
        "emojilabel": "",
        "_id": "5e05760059cad03694db1339",
        "id": "5e05760059cad03694db1339"
      },
      {
        "emojiId": "在干嘛",
        "keyword": "在干嘛",
        "order": 6,
        "wordingText": [
          "[]"
        ],
        "fontcolor": "",
        "backcolor": "",
        "heightItems": "",
        "emojilabel": "",
        "_id": "5e05760059cad03694db133a",
        "id": "5e05760059cad03694db133a"
      },
      {
        "emojiId": "怎么办",
        "keyword": "怎么办",
        "order": 7,
        "wordingText": [
          "[]"
        ],
        "fontcolor": "",
        "backcolor": "",
        "heightItems": "",
        "emojilabel": "",
        "_id": "5e05760059cad03694db133b",
        "id": "5e05760059cad03694db133b"
      },
      {
        "emojiId": "看不下去",
        "keyword": "看不下去",
        "order": 8,
        "wordingText": [
          "[]"
        ],
        "fontcolor": "",
        "backcolor": "",
        "heightItems": "",
        "emojilabel": "",
        "_id": "5e05760059cad03694db133c",
        "id": "5e05760059cad03694db133c"
      },
      {
        "emojiId": "呕呕呕",
        "keyword": "呕呕呕",
        "order": 9,
        "wordingText": [
          "[]"
        ],
        "fontcolor": "",
        "backcolor": "",
        "heightItems": "",
        "emojilabel": "",
        "_id": "5e05760059cad03694db133d",
        "id": "5e05760059cad03694db133d"
      },
      {
        "emojiId": "禁止养猫",
        "keyword": "禁止养猫",
        "order": 10,
        "wordingText": [
          "[]"
        ],
        "fontcolor": "",
        "backcolor": "",
        "heightItems": "",
        "emojilabel": "",
        "_id": "5e05760059cad03694db133e",
        "id": "5e05760059cad03694db133e"
      },
      {
        "emojiId": "我不干了",
        "keyword": "我不干了",
        "order": 11,
        "wordingText": [
          "[]"
        ],
        "fontcolor": "",
        "backcolor": "",
        "heightItems": "",
        "emojilabel": "",
        "_id": "5e05760059cad03694db133f",
        "id": "5e05760059cad03694db133f"
      },
      {
        "emojiId": "休息一下",
        "keyword": "休息一下",
        "order": 12,
        "wordingText": [
          "[]"
        ],
        "fontcolor": "",
        "backcolor": "",
        "heightItems": "",
        "emojilabel": "",
        "_id": "5e05760059cad03694db1340",
        "id": "5e05760059cad03694db1340"
      },
      {
        "emojiId": "吃烧烤",
        "keyword": "吃烧烤",
        "order": 13,
        "wordingText": [
          "[]"
        ],
        "fontcolor": "",
        "backcolor": "",
        "heightItems": "",
        "emojilabel": "",
        "_id": "5e05760059cad03694db1341",
        "id": "5e05760059cad03694db1341"
      },
      {
        "emojiId": "冲",
        "keyword": "冲",
        "order": 14,
        "wordingText": [
          "[]"
        ],
        "fontcolor": "",
        "backcolor": "",
        "heightItems": "",
        "emojilabel": "",
        "_id": "5e05760059cad03694db1342",
        "id": "5e05760059cad03694db1342"
      },
      {
        "emojiId": "愁眉苦脸",
        "keyword": "愁眉苦脸",
        "order": 15,
        "wordingText": [
          "[]"
        ],
        "fontcolor": "",
        "backcolor": "",
        "heightItems": "",
        "emojilabel": "",
        "_id": "5e05760059cad03694db1343",
        "id": "5e05760059cad03694db1343"
      },
      {
        "emojiId": "太刺眼了",
        "keyword": "太刺眼了",
        "order": 16,
        "wordingText": [
          "[]"
        ],
        "fontcolor": "",
        "backcolor": "",
        "heightItems": "",
        "emojilabel": "",
        "_id": "5e05760059cad03694db1344",
        "id": "5e05760059cad03694db1344"
      }
    ],
    "md5Info": [
      {
        "name": "你说什么",
        "md5": "a5db69fcbff77a39fc469864b4706aa6"
      },
      {
        "name": "咻",
        "md5": "7331d0941374f63b78646baad1c5b476"
      },
      {
        "name": "哥俩好",
        "md5": "d4fbc488033a824806e5f51888ee5793"
      },
      {
        "name": "在干嘛",
        "md5": "d824659ef8ffbe772dba1b9c69ffe79a"
      },
      {
        "name": "怎么办",
        "md5": "cbe19c92d6d9edde4aeca38bfa99786f"
      },
      {
        "name": "看不下去",
        "md5": "f7e3c67bc30bf9eaedb55fb85e5a39ea"
      },
      {
        "name": "呕呕呕",
        "md5": "a6b7a79a916d581f2e7b3a920d43eedd"
      },
      {
        "name": "禁止养猫",
        "md5": "2c45ce42f18ece3fd94d14f1e3b1d663"
      },
      {
        "name": "我不干了",
        "md5": "b96a531a18b4a8ae2425eefd14ae44a3"
      },
      {
        "name": "休息一下",
        "md5": "ccb93de3076f3f1a042509d5ba72e5f9"
      },
      {
        "name": "吃烧烤",
        "md5": "85d688dc1086cc604a2e295df8d94f37"
      },
      {
        "name": "冲",
        "md5": "6d2a76dc1bac32d145d95c494cc7b90b"
      },
      {
        "name": "愁眉苦脸",
        "md5": "79ecd52993b4c9f483d8546571ccf022"
      },
      {
        "name": "太刺眼了",
        "md5": "3651bf7225c1a047c1912b21382463b2"
      },
      {
        "name": "认真",
        "md5": "7bf281d0e6e0ae722a704f7a8dbc1bcf"
      },
      {
        "name": "问号",
        "md5": "b32ddb711507ac2e32c42a79f24c4aad"
      }
    ],
    "__bgColors": {}
  }
}
